{"printDate":"2025-10-21","editor":"Ian Livengood","easy":{"id":60,"backendId":"540bd1e9a8525461bc9feb574eeea0be","constructors":"Rodolfo Kurchan","dominoes":[[4,5],[0,3],[5,1],[3,5],[6,6]],"regions":[{"indices":[[0,0],[1,0]],"type":"sum","target":8},{"indices":[[0,1],[0,2],[0,3]],"type":"sum","target":16},{"indices":[[2,0],[3,0]],"type":"less","target":2},{"indices":[[2,1]],"type":"empty"},{"indices":[[2,2]],"type":"greater","target":4},{"indices":[[4,0]],"type":"empty"}],"solution":[[[0,1],[0,0]],[[2,0],[1,0]],[[4,0],[3,0]],[[2,1],[2,2]],[[0,2],[0,3]]]},"medium":{"id":237,"backendId":"65a58c3e750b55e18556bf584f609c22","constructors":"Rodolfo Kurchan","dominoes":[[2,6],[1,3],[0,3],[2,2],[5,4],[0,1],[5,5],[3,2]],"regions":[{"indices":[[0,3],[0,4]],"type":"equals"},{"indices":[[1,0],[1,1],[1,2],[2,1]],"type":"sum","target":21},{"indices":[[1,3],[2,2],[2,3]],"type":"sum","target":4},{"indices":[[1,4],[2,4],[3,4]],"type":"equals"},{"indices":[[3,1]],"type":"less","target":3},{"indices":[[3,3],[4,3]],"type":"less","target":3},{"indices":[[4,4]],"type":"empty"}],"solution":[[[3,1],[2,1]],[[4,3],[4,4]],[[1,3],[0,3]],[[2,4],[3,4]],[[1,2],[2,2]],[[2,3],[3,3]],[[1,0],[1,1]],[[0,4],[1,4]]]},"hard":{"id":196,"backendId":"7296432dd5da5cdd8a7e7fdeea6713d6","constructors":"Rodolfo Kurchan","dominoes":[[4,4],[6,3],[0,1],[3,4],[6,1],[2,4],[4,6],[0,2],[5,6],[1,1],[3,5],[0,3],[2,2],[3,2],[2,6],[0,5]],"regions":[{"indices":[[0,0],[0,1]],"type":"sum","target":12},{"indices":[[0,2],[0,3]],"type":"sum","target":4},{"indices":[[0,4],[0,5]],"type":"equals"},{"indices":[[0,6],[0,7]],"type":"greater","target":9},{"indices":[[1,0]],"type":"less","target":2},{"indices":[[1,2]],"type":"empty"},{"indices":[[1,5]],"type":"sum","target":1},{"indices":[[1,7]],"type":"less","target":3},{"indices":[[2,2],[2,3],[3,2],[3,3]],"type":"unequal"},{"indices":[[2,4],[2,5],[3,5]],"type":"sum","target":0},{"indices":[[3,4]],"type":"sum","target":1},{"indices":[[4,1],[4,2],[5,2]],"type":"sum","target":18},{"indices":[[4,3],[4,4],[5,3],[5,4]],"type":"equals"},{"indices":[[4,5]],"type":"sum","target":3},{"indices":[[4,6],[5,5],[5,6]],"type":"equals"},{"indices":[[5,1]],"type":"greater","target":4}],"solution":[[[4,3],[4,4]],[[4,2],[3,2]],[[2,5],[1,5]],[[1,2],[2,2]],[[0,0],[1,0]],[[5,5],[5,4]],[[5,3],[5,2]],[[2,4],[2,3]],[[5,1],[4,1]],[[3,3],[3,4]],[[0,5],[0,6]],[[3,5],[4,5]],[[4,6],[5,6]],[[0,4],[0,3]],[[0,2],[0,1]],[[1,7],[0,7]]]}}